TheFunPackage
