Metadata-Version: 2.1
Name: TheFunPackage
Version: 1.0.2
Summary: This package is only meant for fun and to entertain you!
Home-page: https://github.com/TheFunPackage/TheFunPackage-Python
Download-URL: https://pypi.org/project/TheFunPackage
Author: Aniketh Chavare
Author-email: anikethchavare@outlook.com
License: Apache License 2.0
Classifier: Development Status :: 5 - Production/Stable
Classifier: License :: OSI Approved :: Apache Software License
Classifier: Natural Language :: English
Classifier: Operating System :: OS Independent
Classifier: Programming Language :: Python
Classifier: Programming Language :: Python :: 2
Classifier: Programming Language :: Python :: 3
Classifier: Topic :: Games/Entertainment
Classifier: Topic :: Software Development
License-File: LICENSE.txt
